README.md
setup.py
aocqq/__init__.py
python_aoc_qq.egg-info/PKG-INFO
python_aoc_qq.egg-info/SOURCES.txt
python_aoc_qq.egg-info/dependency_links.txt
python_aoc_qq.egg-info/requires.txt
python_aoc_qq.egg-info/top_level.txt