Metadata-Version: 1.1
Name: python-aoc-qq
Version: 1.0.3
Summary: AoC QQ API
Home-page: https://github.com/happyleavesaoc/python-aoc-qq/
Author: happyleaves
Author-email: happyleaves.tfr@gmail.com
License: MIT
Platform: UNKNOWN
Classifier: License :: OSI Approved :: MIT License
Classifier: Operating System :: OS Independent
Classifier: Programming Language :: Python :: 3
